{
  "success": true,
  "research_topic": "natural language processing",
  "execution_time": "0:05:42.586201",
  "statistics": {
    "papers_found": 5,
    "notes_extracted": 32,
    "themes_identified": 4,
    "gaps_identified": 7,
    "citations_generated": 5
  },
  "gaps": [
    "Limited research on longitudinal studies in the current literature",
    "Limited research on clinical trials in the current literature",
    "Limited research on real-world evidence in the current literature",
    "Limited research on cost-effectiveness in the current literature",
    "Limited research on patient outcomes in the current literature",
    "Limited research on implementation challenges in the current literature",
    "Limited research on regulatory considerations in the current literature"
  ]
}